LICENSE.txt
MANIFEST.in
setup.cfg
setup.py
tlux/__init__.py
tlux/__main__.py
tlux/decorators.py
tlux/network.py
tlux/plot.py
tlux/profiling.py
tlux/readme.md
tlux/setup.py
tlux/storage.py
tlux/system.py
tlux.egg-info/PKG-INFO
tlux.egg-info/SOURCES.txt
tlux.egg-info/dependency_links.txt
tlux.egg-info/requires.txt
tlux.egg-info/top_level.txt
tlux/about/author.txt
tlux/about/classifiers.txt
tlux/about/description.txt
tlux/about/keywords.txt
tlux/about/on_pypi.txt
tlux/about/package_name.txt
tlux/about/requirements.txt
tlux/about/version.txt
tlux/about/version_history.md
tlux/approximate/__init__.py
tlux/approximate/base.py
tlux/approximate/nearest_neighbor.py
tlux/approximate/axy/.gitignore
tlux/approximate/axy/__init__.py
tlux/approximate/axy/axy.f90
tlux/approximate/axy/axy_matrix_operations.f90
tlux/approximate/axy/axy_profiler.f90
tlux/approximate/axy/axy_py.py
tlux/approximate/axy/axy_random.f90
tlux/approximate/axy/axy_sort_and_select.f90
tlux/approximate/axy/display.py
tlux/approximate/axy/pcg32.f90
tlux/approximate/axy/preprocessing.py
tlux/approximate/axy/summary.py
tlux/approximate/axy/axy/__init__.py
tlux/approximate/axy/axy/axy.f90
tlux/approximate/axy/axy/axy_c_wrapper.f90
tlux/approximate/axy/axy/axy_matrix_operations.f90
tlux/approximate/axy/axy/axy_profiler.f90
tlux/approximate/axy/axy/axy_python_wrapper.py
tlux/approximate/axy/axy/axy_random.f90
tlux/approximate/axy/axy/axy_sort_and_select.f90
tlux/approximate/axy/axy/pcg32.f90
tlux/approximate/axy/axy_OLD/__init__.py
tlux/approximate/axy/axy_OLD/axy.f90
tlux/approximate/axy/axy_OLD/axy_c_wrapper.f90
tlux/approximate/axy/axy_OLD/axy_matrix_operations.f90
tlux/approximate/axy/axy_OLD/axy_profiler.f90
tlux/approximate/axy/axy_OLD/axy_python_wrapper.py
tlux/approximate/axy/axy_OLD/axy_random.f90
tlux/approximate/axy/axy_OLD/axy_sort_and_select.f90
tlux/approximate/axy/axy_OLD/pcg32.f90
tlux/approximate/axy/axy_random/__init__.py
tlux/approximate/axy/axy_random/axy_random.f90
tlux/approximate/axy/axy_random/axy_random_c_wrapper.f90
tlux/approximate/axy/axy_random/axy_random_python_wrapper.py
tlux/approximate/axy/axy_random/pcg32.f90
